useragents_me_scraper/__init__.py
useragents_me_scraper/useragents.py
useragents_me_scraper/utils.py
useragents_me_scraper-0.1.4.dist-info/METADATA
useragents_me_scraper-0.1.4.dist-info/WHEEL
useragents_me_scraper-0.1.4.dist-info/licenses/LICENSE
useragents_me_scraper-0.1.4.dist-info/RECORD
